logging_mp/__init__.py
logging_mp-0.1.6.dist-info/METADATA
logging_mp-0.1.6.dist-info/WHEEL
logging_mp-0.1.6.dist-info/top_level.txt
logging_mp-0.1.6.dist-info/RECORD
