Metadata-Version: 2.1
Name: logging-mp
Version: 0.1.6
Summary: A multiprocessing-safe logging system with Rich support.
Author-email: silencht <silencht@qq.com>
License: MIT
Project-URL: Homepage, https://github.com/silencht/logging-mp
Requires-Python: >=3.8
Requires-Dist: rich >=13.0
